reahl/dev/__init__.py
reahl/dev/devdomain.py
reahl/dev/devshell.py
reahl/dev/exceptions.py
reahl/dev/fixtures.py
reahl/dev/mailtest.py
reahl/dev/pytestmonkeypatch.py
reahl/dev/tools.py
reahl/dev_dev/__init__.py
reahl/dev_dev/building_and_distributing_packages.puml
reahl/dev_dev/egg_and_chicken_projects.puml
reahl/dev_dev/projects_and_project_related_metadata.puml
reahl/dev_dev/projects_and_workspace.puml
reahl/dev_dev/test_context.py
reahl/dev_dev/test_domain.py
reahl/dev_dev/test_git.py
reahl/dev_dev/versioning_and_dependency_meta_data.puml
reahl_dev-7.0.3.dist-info/LICENSE
reahl_dev-7.0.3.dist-info/METADATA
reahl_dev-7.0.3.dist-info/WHEEL
reahl_dev-7.0.3.dist-info/entry_points.txt
reahl_dev-7.0.3.dist-info/reahl-component.toml
reahl_dev-7.0.3.dist-info/top_level.txt
reahl_dev-7.0.3.dist-info/RECORD
